README.md
setup.cfg
setup.py
vectordash/__init__.py
vectordash/main.py
vectordash.egg-info/PKG-INFO
vectordash.egg-info/SOURCES.txt
vectordash.egg-info/dependency_links.txt
vectordash.egg-info/entry_points.txt
vectordash.egg-info/not-zip-safe
vectordash.egg-info/requires.txt
vectordash.egg-info/top_level.txt
vectordash/cli/__init__.py
vectordash/cli/jupyter.py
vectordash/cli/list.py
vectordash/cli/login.py
vectordash/cli/pull.py
vectordash/cli/push.py
vectordash/cli/ssh.py