Metadata-Version: 1.0
Name: vectordash
Version: 1.9.4
Summary: Command line interface for interacting with Vectordash GPUs.
Home-page: https://github.com/Vectordash/vectordash-cli
Author: Arbaz Khatib
Author-email: arbaz@vectordash.com
License: UNKNOWN
Keywords: vectordash
Platform: UNKNOWN
